{
  "as_of": "2026-04-03",
  "source_notes": {
    "price": "placeholder (to be replaced by public API)",
    "distribution": "placeholder (to be replaced by public data or issuer)",
    "covered_call_ratio": "optional for high dividend ETF (e.g., dividend yield)",
    "expense_ratio": "placeholder"
  },
  "etfs": [
    {
      "id": "KRX:000000",
      "ticker": "000000",
      "name_ko": "배당 ETF 샘플 (자동 갱신 예정)",
      "issuer": null,
      "listed_date": null,
      "expense_ratio": null,
      "price": {
        "close": null,
        "change": null,
        "change_pct": null,
        "volume": null,
        "market_cap": null,
        "date": null
      },
      "distribution": {
        "latest_amount": null,
        "latest_record_date": null,
        "latest_pay_date": null,
        "frequency": null,
        "currency": "KRW"
      },
      "covered_call_ratio": {
        "value": null,
        "unit": "percent",
        "date": null,
        "method": "not_available"
      },
      "links": {
        "issuer": null,
        "factsheet": null,
        "disclosure": null
      }
    }
  ]
}
